.DS_Store
aix/__init__.py
aix/resource.py
aixapi/__init__.py
aixapi/resource.py
spontit/__init__.py
spontit/examples.py
spontit/resource.py
spontit/util.py
spontit/examples/__init__.py
spontit/examples/dirty_image_upload_example.py
spontit/examples/examples.py
spontit_pkg/__init__.py
spontit_pkg/resource.py
spontit_pkg/util.py
aixapi-0.0.5.dist-info/LICENSE
aixapi-0.0.5.dist-info/METADATA
aixapi-0.0.5.dist-info/WHEEL
aixapi-0.0.5.dist-info/top_level.txt
aixapi-0.0.5.dist-info/RECORD
