Metadata-Version: 2.1
Name: aixapi
Version: 0.0.5
Summary: AI for everyone. With this API, you can access GPT-J. GPT-J is as powerful as OpenAI's GPT-3 Curie engine.
Home-page: https://github.com/AIx-Solutions/aix-gpt-api
Author: AIx Solutions Group, Inc
Author-email: info@aixsolutionsgroup.com
License: UNKNOWN
Platform: UNKNOWN
Classifier: Programming Language :: Python :: 3
Classifier: License :: OSI Approved :: MIT License
Classifier: Operating System :: OS Independent
Requires-Python: >=3.6
Requires-Dist: requests
